s3_browser/Welcome.py
s3_browser/__init__.py
s3_browser/common/__init__.py
s3_browser/common/s3_client.py
s3_browser/pages/1_Explorer.py
s3_browser/pages/2_Policy.py
s3_browser_cli/cli.py
s3_browser_cli-0.0.7.dist-info/METADATA
s3_browser_cli-0.0.7.dist-info/WHEEL
s3_browser_cli-0.0.7.dist-info/entry_points.txt
s3_browser_cli-0.0.7.dist-info/RECORD
