Metadata-Version: 2.1
Name: s3-browser-cli
Version: 0.0.7
Summary: 
Author: Chaobin Zhang
Author-email: zhchbin@gmail.com
Requires-Python: >=3.10,<4.0
Classifier: Programming Language :: Python :: 3
Classifier: Programming Language :: Python :: 3.10
Classifier: Programming Language :: Python :: 3.11
Requires-Dist: boto3 (>=1.28.32,<2.0.0)
Requires-Dist: click (>=8.1.7,<9.0.0)
Requires-Dist: humanize (>=4.8.0,<5.0.0)
Requires-Dist: streamlit (>=1.25.0,<2.0.0)
Requires-Dist: streamlit-code-editor (>=0.1.8,<0.2.0)
Requires-Dist: watchdog (>=3.0.0,<4.0.0)
